LICENSE
README.md
setup.py
pyfvvdp/__init__.py
pyfvvdp/fvvdp.py
pyfvvdp/fvvdp_display_model.py
pyfvvdp/fvvdp_lpyr_dec.py
pyfvvdp/fvvdp_test.py
pyfvvdp/interp.py
pyfvvdp/pupsnr.py
pyfvvdp/run_fvvdp.py
pyfvvdp/utils.py
pyfvvdp/video_source.py
pyfvvdp/video_source_file.py
pyfvvdp/video_source_yuv.py
pyfvvdp/visualize_diff_map.py
pyfvvdp.egg-info/PKG-INFO
pyfvvdp.egg-info/SOURCES.txt
pyfvvdp.egg-info/dependency_links.txt
pyfvvdp.egg-info/entry_points.txt
pyfvvdp.egg-info/requires.txt
pyfvvdp.egg-info/top_level.txt
pyfvvdp/csf_cache/o0_sn1_5_cm0_604562_gpu0.mat
pyfvvdp/csf_cache/o5_sn1_5_cm0_604562_gpu0.mat
pyfvvdp/fvvdp_data/color_spaces.json
pyfvvdp/fvvdp_data/display_models.json
pyfvvdp/fvvdp_data/fvvdp_parameters.json
pyfvvdp/fvvdp_data/fvvdp_parameters_1_0.json
pyfvvdp/third_party/__init__.py
pyfvvdp/third_party/cpuinfo.py
pyfvvdp/third_party/loadmat.py