Metadata-Version: 2.1
Name: pyfvvdp
Version: 1.2.2
Summary: PyTorch code for 'FovVideoVDP': a full-referencevisual quality metric that predicts the perceptualdifference between pairs of images or videos.
Home-page: https://github.com/gfxdisp/FovVideoVDP
Author: Rafał K. Mantiuk
Author-email: mantiuk@gmail.com
License: Creative Commons Attribution-NonCommercial 4.0 International Public License
Classifier: Development Status :: 4 - Beta
Classifier: Intended Audience :: Science/Research
Classifier: Operating System :: OS Independent
Classifier: Environment :: GPU :: NVIDIA CUDA
Classifier: Programming Language :: Python :: 3.8
Classifier: Programming Language :: Python :: 3.9
Classifier: Programming Language :: Python :: 3.10
License-File: LICENSE
